dockstrap
