Metadata-Version: 1.0
Name: dockstrap
Version: 0.2
Summary: Like debootstrap but uses docker registry
Home-page: UNKNOWN
Author: Unbit
Author-email: info@unbit.it
License: MIT
Platform: UNKNOWN
